tests/__init__.py
tests/test_anno_dict_based.py
tests/test_anno_obj_based.py
tests/test_cap_dict_based.py
tests/test_cap_obj_based.py
tests/test_cmt_params_dict_based.py
tests/test_cmt_params_obj_based.py
tests/test_parser_dict_based.py
tests/test_parser_obj_based.py
typed_cap/__init__.py
typed_cap/_version.py
typed_cap/anno.py
typed_cap/args_parser.py
typed_cap/cap.py
typed_cap/cmt_param.py
typed_cap/types.py
typed_cap/typing.py
typed_cap/typing/__init__.py
typed_cap/typing/default.py
typed_cap/typing/types.py
typed_cap/typing/utils.py
typed_cap/typing/valid.py
typed_cap/utils/__init__.py
typed_cap/utils/code.py
typed_cap/utils/color.py
typed_cap/utils/option.py
typed_cap-0.3.1.dist-info/LICENSE
typed_cap-0.3.1.dist-info/METADATA
typed_cap-0.3.1.dist-info/WHEEL
typed_cap-0.3.1.dist-info/top_level.txt
typed_cap-0.3.1.dist-info/RECORD
