Metadata-Version: 2.1
Name: typed-cap
Version: 0.3.1
Summary: typed command line argument parser
Home-page: https://github.com/MamoruDS/typed-cap
Author: MamoruDS
Author-email: mamoruds.io@gmail.com
Classifier: License :: OSI Approved :: MIT License
Classifier: Operating System :: OS Independent
Classifier: Programming Language :: Python :: 3
Classifier: Programming Language :: Python :: 3.9
Classifier: Programming Language :: Python :: 3.10
Requires-Python: >=3.9
License-File: LICENSE
